queryset_gallery/__init__.py
queryset_gallery/filters.py
queryset_gallery/gallery.py
queryset_gallery/paginator.py
queryset_gallery/tests.py
django_queryset_gallery-1.1.3.dist-info/LICENSE
django_queryset_gallery-1.1.3.dist-info/METADATA
django_queryset_gallery-1.1.3.dist-info/WHEEL
django_queryset_gallery-1.1.3.dist-info/top_level.txt
django_queryset_gallery-1.1.3.dist-info/RECORD
