Metadata-Version: 2.1
Name: django-queryset-gallery
Version: 1.1.3
Summary: Queryset gallery is an interface for creating a gallery that provides pagination and filtering via lookups. It can be useful for getting objects via API.
Home-page: https://github.com/eumozge/django-queryset-gallery
Author: Eugene Mozge
Author-email: eumozge@gmail.com
License: UNKNOWN
Platform: UNKNOWN
Classifier: Development Status :: 5 - Production/Stable
Classifier: Programming Language :: Python :: 3
Classifier: License :: OSI Approved :: MIT License
Classifier: Operating System :: OS Independent
